pytorch_partial_crf/__init__.py
pytorch_partial_crf/base_crf.py
pytorch_partial_crf/crf.py
pytorch_partial_crf/marginal_crf.py
pytorch_partial_crf/partial_crf.py
pytorch_partial_crf/utils.py
pytorch_partial_crf-0.2.1.dist-info/LICENSE.txt
pytorch_partial_crf-0.2.1.dist-info/WHEEL
pytorch_partial_crf-0.2.1.dist-info/METADATA
pytorch_partial_crf-0.2.1.dist-info/RECORD
