Metadata-Version: 2.1
Name: pytorch-partial-crf
Version: 0.2.1
Summary: 
Home-page: https://github.com/kajyuuen/pytorch-partial-crf
License: MIT
Author: Koga Kobayashi
Author-email: kajyuuen@gmail.com
Requires-Python: >=3.8,<4.0
Classifier: License :: OSI Approved :: MIT License
Classifier: Programming Language :: Python :: 3
Classifier: Programming Language :: Python :: 3.8
Classifier: Programming Language :: Python :: 3.9
Classifier: Programming Language :: Python :: 3.10
Requires-Dist: pytest (>=6.2.5,<7.0.0)
Requires-Dist: torch (>=1.10.0,<2.0.0)
Project-URL: Repository, https://github.com/kajyuuen/pytorch-partial-crf
